motionshader/__init__.py
motionshader/core.py
motionshader-1.1.0.dist-info/LICENSE
motionshader-1.1.0.dist-info/METADATA
motionshader-1.1.0.dist-info/WHEEL
motionshader-1.1.0.dist-info/top_level.txt
motionshader-1.1.0.dist-info/RECORD
