Metadata-Version: 2.1
Name: motionshader
Version: 1.1.0
Summary: Generate a gif or mp4 from geospatial vector data.
Home-page: https://github.com/hokieg3n1us/motionshader
Author: Barry Bragg
Author-email: hokieg3n1us@gmail.com
License: UNKNOWN
Platform: UNKNOWN
Classifier: Programming Language :: Python :: 3
Classifier: License :: OSI Approved :: MIT License
Classifier: Operating System :: OS Independent
Requires-Python: >=3.6
Requires-Dist: datashader
Requires-Dist: imageio
Requires-Dist: imageio-ffmpeg
